pyovf/__init__.py
pyovf/_ovf_core.cpython-314-darwin.so
pyovf/_version.py
pyovf/helper_funcs.py
pyovf/ovf_handler.py
pyovf-0.2.10.dist-info/licenses/LICENSE
pyovf-0.2.10.dist-info/METADATA
pyovf-0.2.10.dist-info/WHEEL
pyovf-0.2.10.dist-info/top_level.txt
pyovf-0.2.10.dist-info/RECORD
