Metadata-Version: 2.4
Name: pyovf
Version: 0.2.10
Summary: Python library for reading and writing OVF (OOMMF Vector Field) files
Author-email: Flavio Abreu Araujo <flavio.abreuaraujo@uclouvain.be>
Maintainer-email: Flavio Abreu Araujo <flavio.abreuaraujo@uclouvain.be>
License-Expression: MIT
Project-URL: Homepage, https://gitlab.flavio.be/flavio/pyovf
Project-URL: Documentation, https://gitlab.flavio.be/flavio/pyovf/-/blob/main/README.md
Project-URL: Repository, https://gitlab.flavio.be/flavio/pyovf.git
Project-URL: Issues, https://gitlab.flavio.be/flavio/pyovf/-/issues
Keywords: ovf,oommf,mumax3,micromagnetics,magnetism,scientific-computing
Classifier: Development Status :: 4 - Beta
Classifier: Intended Audience :: Science/Research
Classifier: Operating System :: OS Independent
Classifier: Programming Language :: Python :: 3
Classifier: Programming Language :: Python :: 3.8
Classifier: Programming Language :: Python :: 3.9
Classifier: Programming Language :: Python :: 3.10
Classifier: Programming Language :: Python :: 3.11
Classifier: Programming Language :: Python :: 3.12
Classifier: Programming Language :: Python :: 3.13
Classifier: Programming Language :: Python :: 3.14
Classifier: Programming Language :: C++
Classifier: Topic :: Scientific/Engineering :: Physics
Requires-Python: >=3.8
License-File: LICENSE
Requires-Dist: numpy>=2.0.2
Provides-Extra: dev
Requires-Dist: pytest>=9.0.2; extra == "dev"
Requires-Dist: pytest-cov>=7.0.0; extra == "dev"
Requires-Dist: black>=25.12.0; extra == "dev"
Requires-Dist: isort>=7.0.0; extra == "dev"
Requires-Dist: mypy>=1.0; extra == "dev"
Requires-Dist: ruff>=0.1.0; extra == "dev"
Provides-Extra: docs
Requires-Dist: sphinx>=9.1.0; extra == "docs"
Requires-Dist: sphinx-rtd-theme>=3.0.2; extra == "docs"
Requires-Dist: myst-parser>=4.0.1; extra == "docs"
Dynamic: license-file
